odoo/addons/subscription_oca/README.rst
odoo/addons/subscription_oca/__init__.py
odoo/addons/subscription_oca/__manifest__.py
odoo/addons/subscription_oca/data/ir_cron.xml
odoo/addons/subscription_oca/data/sale_subscription_data.xml
odoo/addons/subscription_oca/i18n/es.po
odoo/addons/subscription_oca/i18n/it.po
odoo/addons/subscription_oca/i18n/subscription_oca.pot
odoo/addons/subscription_oca/models/__init__.py
odoo/addons/subscription_oca/models/account_move.py
odoo/addons/subscription_oca/models/product_template.py
odoo/addons/subscription_oca/models/res_partner.py
odoo/addons/subscription_oca/models/sale_order.py
odoo/addons/subscription_oca/models/sale_order_line.py
odoo/addons/subscription_oca/models/sale_subscription.py
odoo/addons/subscription_oca/models/sale_subscription_close_reason.py
odoo/addons/subscription_oca/models/sale_subscription_line.py
odoo/addons/subscription_oca/models/sale_subscription_stage.py
odoo/addons/subscription_oca/models/sale_subscription_tag.py
odoo/addons/subscription_oca/models/sale_subscription_template.py
odoo/addons/subscription_oca/readme/CONTRIBUTORS.rst
odoo/addons/subscription_oca/readme/DESCRIPTION.rst
odoo/addons/subscription_oca/readme/ROADMAP.rst
odoo/addons/subscription_oca/readme/USAGE.rst
odoo/addons/subscription_oca/security/ir.model.access.csv
odoo/addons/subscription_oca/security/ir_rule.xml
odoo/addons/subscription_oca/static/description/icon.png
odoo/addons/subscription_oca/static/description/index.html
odoo/addons/subscription_oca/static/img/icon.png
odoo/addons/subscription_oca/tests/__init__.py
odoo/addons/subscription_oca/tests/test_subscription_oca.py
odoo/addons/subscription_oca/views/product_template_views.xml
odoo/addons/subscription_oca/views/res_partner_views.xml
odoo/addons/subscription_oca/views/sale_order_views.xml
odoo/addons/subscription_oca/views/sale_subscription_stage_views.xml
odoo/addons/subscription_oca/views/sale_subscription_tag_views.xml
odoo14_addon_subscription_oca-14.0.1.3.0.dist-info/METADATA
odoo14_addon_subscription_oca-14.0.1.3.0.dist-info/WHEEL
odoo14_addon_subscription_oca-14.0.1.3.0.dist-info/top_level.txt
odoo14_addon_subscription_oca-14.0.1.3.0.dist-info/RECORD
